juppy/__init__.py
juppy-0.0a1.dist-info/LICENSE
juppy-0.0a1.dist-info/METADATA
juppy-0.0a1.dist-info/WHEEL
juppy-0.0a1.dist-info/top_level.txt
juppy-0.0a1.dist-info/RECORD
